discode/__init__.py
discode/_http.py
discode/abc.py
discode/activity.py
discode/base_events.py
discode/channel.py
discode/client.py
discode/colours.py
discode/components.py
discode/embeds.py
discode/errors.py
discode/guild.py
discode/gw.py
discode/intents.py
discode/interaction.py
discode/member.py
discode/message.py
discode/styles.py
discode/user.py
discode/utils.py
discode/commands/__init__.py
discode/commands/bot.py
discode/commands/command.py
Discode.py-1.1.1.dist-info/LICENSE
Discode.py-1.1.1.dist-info/METADATA
Discode.py-1.1.1.dist-info/WHEEL
Discode.py-1.1.1.dist-info/top_level.txt
Discode.py-1.1.1.dist-info/RECORD
