Metadata-Version: 2.1
Name: Discode.py
Version: 1.1.1
Summary: Asynchronous Python API wrapper for the Discord Gateway API and Discord REST API.
Home-page: https://github.com/thefargg/discode
Author: TheFarGG
Maintainer: TheFarGG
License: MIT
Keywords: Discode,discode,Discord,discord
Platform: UNKNOWN
Classifier: License :: OSI Approved :: MIT License
Classifier: Programming Language :: Python :: 3.7
Classifier: Programming Language :: Python :: 3.8
Classifier: Programming Language :: Python :: 3.9
Classifier: Programming Language :: Python :: 3.10
Classifier: Operating System :: OS Independent
Classifier: Topic :: Internet
Classifier: Topic :: Utilities
Requires-Python: >=3.7.0
Requires-Dist: aiohttp
Requires-Dist: websockets
Provides-Extra: docs
Requires-Dist: sphinx ; extra == 'docs'
Requires-Dist: furo ; extra == 'docs'
